agent/__init__.py
jiangjinjiu-2025.2.2.dist-info/METADATA
jiangjinjiu-2025.2.2.dist-info/WHEEL
jiangjinjiu-2025.2.2.dist-info/entry_points.txt
web/__init__.py
web/app.py
jiangjinjiu-2025.2.2.dist-info/RECORD
