Metadata-Version: 2.1
Name: jiangjinjiu
Version: 2025.2.2
Summary: A Consumer Portal
Author-Email: libai1222 <libai1222@qq.com>
License: MIT
Requires-Python: >=3.12
